fasthttp/__init__.py
fasthttp/applications.py
fasthttp/lifecycle.py
fasthttp/serializers.py
fastaiohttp-0.1.11.dist-info/METADATA
fastaiohttp-0.1.11.dist-info/WHEEL
fastaiohttp-0.1.11.dist-info/licenses/LICENSE
fastaiohttp-0.1.11.dist-info/RECORD
