Metadata-Version: 2.4
Name: fastaiohttp
Version: 0.1.11
Summary: A fast and elegant HTTP client library with decorator-based request handling built on aiohttp
Project-URL: Homepage, https://github.com/2-seo/fasthttp
Project-URL: Repository, https://github.com/2-seo/fasthttp
Project-URL: Issues, https://github.com/2-seo/fasthttp/issues
Author-email: FastHTTP Team <seohyun.develop@gmail.com>
License-Expression: MIT
License-File: LICENSE
Keywords: aiohttp,api,async,client,decorator,http,requests
Classifier: Development Status :: 4 - Beta
Classifier: Intended Audience :: Developers
Classifier: License :: OSI Approved :: MIT License
Classifier: Programming Language :: Python :: 3
Classifier: Programming Language :: Python :: 3.8
Classifier: Programming Language :: Python :: 3.9
Classifier: Programming Language :: Python :: 3.10
Classifier: Programming Language :: Python :: 3.11
Classifier: Programming Language :: Python :: 3.12
Classifier: Programming Language :: Python :: 3.13
Classifier: Topic :: Internet :: WWW/HTTP
Classifier: Topic :: Software Development :: Libraries :: Python Modules
Requires-Python: >=3.8
Requires-Dist: aiohttp>=3.8.0
